py_psscriptanalyzer/__init__.py
py_psscriptanalyzer/__main__.py
py_psscriptanalyzer/cli.py
py_psscriptanalyzer/constants.py
py_psscriptanalyzer/core.py
py_psscriptanalyzer/powershell.py
py_psscriptanalyzer/scripts.py
py_psscriptanalyzer-0.3.1.dist-info/METADATA
py_psscriptanalyzer-0.3.1.dist-info/WHEEL
py_psscriptanalyzer-0.3.1.dist-info/entry_points.txt
py_psscriptanalyzer-0.3.1.dist-info/licenses/LICENSE
py_psscriptanalyzer-0.3.1.dist-info/RECORD
