Metadata-Version: 2.1
Name: py-psscriptanalyzer
Version: 0.3.1
Summary: Python wrapper for PowerShell PSScriptAnalyzer - static analysis and formatting for PowerShell scripts
Project-URL: Homepage, https://github.com/thetestlabs/py-psscriptanalyzer
Project-URL: Repository, https://github.com/thetestlabs/py-psscriptanalyzer
Project-URL: Issues, https://github.com/thetestlabs/py-psscriptanalyzer/issues
Project-URL: Documentation, https://py-psscriptanalyzer.thetestlabs.io/
Project-URL: Changelog, https://github.com/thetestlabs/py-psscriptanalyzer/blob/main/CHANGELOG.md
Author-email: Chris McQuaid <chris@thetestlabs.io>
Maintainer-email: Chris McQuaid <chris@thetestlabs.io>
License: MIT
License-File: LICENSE
Keywords: automation,ci-cd,code-quality,formatting,linting,powershell,pre-commit,psscriptanalyzer,static-analysis
Classifier: Development Status :: 4 - Beta
Classifier: Environment :: Console
Classifier: Intended Audience :: Developers
Classifier: License :: OSI Approved :: MIT License
Classifier: Operating System :: OS Independent
Classifier: Programming Language :: Python :: 3
Classifier: Programming Language :: Python :: 3.9
Classifier: Programming Language :: Python :: 3.10
Classifier: Programming Language :: Python :: 3.11
Classifier: Programming Language :: Python :: 3.12
Classifier: Programming Language :: Python :: 3.13
Classifier: Topic :: Software Development :: Quality Assurance
Classifier: Topic :: Software Development :: Testing
Classifier: Topic :: Text Processing :: Linguistic
Classifier: Typing :: Typed
Requires-Python: >=3.9
Requires-Dist: rich>=10.0.0
Provides-Extra: dev
Requires-Dist: build>=1.3.0; extra == 'dev'
Requires-Dist: mypy>=1.17.1; extra == 'dev'
Requires-Dist: pre-commit>=4.2.0; extra == 'dev'
Requires-Dist: pytest-cov>=6.2.1; extra == 'dev'
Requires-Dist: pytest>=8.4.1; extra == 'dev'
Requires-Dist: ruff>=0.12.7; extra == 'dev'
Requires-Dist: twine>=6.1.0; extra == 'dev'
Provides-Extra: docs
Requires-Dist: linkify-it-py>=2.0.0; extra == 'docs'
Requires-Dist: myst-parser>=3.0.1; extra == 'docs'
Requires-Dist: sphinx-autodoc-typehints>=2.3.0; extra == 'docs'
Requires-Dist: sphinx-copybutton>=0.5.2; extra == 'docs'
Requires-Dist: sphinx-rtd-theme>=2.0.0; extra == 'docs'
Requires-Dist: sphinx>=7.1.0; extra == 'docs'
